machine_learning_comparison_pipeline/__init__.py
machine_learning_comparison_pipeline/pipeline.py
MachineLearningComparisonPipeline-0.2.4.dist-info/METADATA
MachineLearningComparisonPipeline-0.2.4.dist-info/WHEEL
MachineLearningComparisonPipeline-0.2.4.dist-info/top_level.txt
MachineLearningComparisonPipeline-0.2.4.dist-info/RECORD
