Metadata-Version: 2.1
Name: MachineLearningComparisonPipeline
Version: 0.2.4
Summary: Pipeline for analysis of the machine learning applications in Sci-Kit Learn
Author-email: "Dr. Frank Mobley" <frank.mobley.1@afrl.af.mil>, Gregory Bowers <gregory.bowers.ctr@us.af.mil>
License: MIT
Project-URL: Homepage, https://gitlab.com/python-audio-feature-extraction/machine-learning-pipeline
Keywords: machine learning,feature extraction,audio
Requires-Python: >=3.7
Requires-Dist: numpy >=1.21.5
Requires-Dist: pandas >=1.4.3
Requires-Dist: scipy >=1.9.1
Requires-Dist: statsmodels >=0.13.2
Requires-Dist: scikit-learn >=1.1.0
Requires-Dist: salib >=1.1.1
Requires-Dist: tqdm >=4.50.0
Requires-Dist: json5 >=0.9.0
Requires-Dist: bottleneck >=1.3.6
